utils_ak/.DS_Store
utils_ak/__init__.py
utils_ak/architecture/VERSION
utils_ak/architecture/__init__.py
utils_ak/architecture/finite_state_machine/__init__.py
utils_ak/architecture/finite_state_machine/finite_state_machine.py
utils_ak/architecture/func/__init__.py
utils_ak/architecture/func/handler.py
utils_ak/architecture/func/pipeline.py
utils_ak/architecture/func/test_handler.py
utils_ak/architecture/func/topic_handler.py
utils_ak/architecture/integrity_guard/__init__.py
utils_ak/architecture/integrity_guard/filesystem_integrity_guard.py
utils_ak/architecture/integrity_guard/integrity_guard.py
utils_ak/architecture/operation/__init__.py
utils_ak/architecture/operation/operation.py
utils_ak/architecture/sink/__init__.py
utils_ak/architecture/sink/return_values_sink.py
utils_ak/async_tools/VERSION
utils_ak/async_tools/__init__.py
utils_ak/async_tools/async_tools.py
utils_ak/block_tree/VERSION
utils_ak/block_tree/__init__.py
utils_ak/block_tree/block.py
utils_ak/block_tree/maker.py
utils_ak/block_tree/parallelepiped_block.py
utils_ak/block_tree/pushers/__init__.py
utils_ak/block_tree/pushers/dummy.py
utils_ak/block_tree/pushers/iterative.py
utils_ak/block_tree/pushers/pushers.py
utils_ak/block_tree/validation.py
utils_ak/builtin/VERSION
utils_ak/builtin/__init__.py
utils_ak/builtin/collection.py
utils_ak/callback_timer/VERSION
utils_ak/callback_timer/__init__.py
utils_ak/callback_timer/callback_timer.py
utils_ak/clickhouse/.gitignore
utils_ak/clickhouse/VERSION
utils_ak/clickhouse/__init__.py
utils_ak/clickhouse/config/__init__.py
utils_ak/clickhouse/config/config.py
utils_ak/clickhouse/ingest.py
utils_ak/clock/VERSION
utils_ak/clock/__init__.py
utils_ak/clock/clock.json
utils_ak/clock/clock.py
utils_ak/coder/VERSION
utils_ak/coder/__init__.py
utils_ak/coder/binary.py
utils_ak/coder/coder.py
utils_ak/coder/coders/__init__.py
utils_ak/coder/coders/json/__init__.py
utils_ak/coder/coders/json/json_coder.py
utils_ak/coder/coders/msgpack/__init__.py
utils_ak-0.1.13.dist-info/WHEEL
utils_ak-0.1.13.dist-info/METADATA
utils_ak-0.1.13.dist-info/RECORD
